cli_bundle/__init__.py
cli_bundle/cli.py
cli_bundle/cli_help.py
cli_bundle/dereberus.py
dereberus-2.3.dist-info/METADATA
dereberus-2.3.dist-info/WHEEL
dereberus-2.3.dist-info/entry_points.txt
dereberus-2.3.dist-info/top_level.txt
dereberus-2.3.dist-info/RECORD
