Metadata-Version: 2.4
Name: dereberus
Version: 2.3
Requires-Dist: click
Requires-Dist: tabulate
Requires-Dist: pathlib
Requires-Dist: requests
Requires-Dist: fpdf
Dynamic: requires-dist
